httpie_hush.py
httpie_hush-1.3.dist-info/METADATA
httpie_hush-1.3.dist-info/WHEEL
httpie_hush-1.3.dist-info/entry_points.txt
httpie_hush-1.3.dist-info/licenses/LICENSE
httpie_hush-1.3.dist-info/RECORD
