Metadata-Version: 2.4
Name: httpie-hush
Version: 1.3
Summary: Hush OAuth 2 plugin for the HTTPie command line HTTP client
License-File: LICENSE
Author: Gilad Sever
Author-email: gilad9366@gmail.com
Requires-Python: >=3.12,<4.0
Classifier: Programming Language :: Python :: 3
Classifier: Programming Language :: Python :: 3.12
Classifier: Programming Language :: Python :: 3.13
Classifier: Programming Language :: Python :: 3.14
Requires-Dist: httpie (>=3.2.4,<4.0.0)
